remove_outliers/outlier_remover.py
remove_outliers/remove.py
remove_outliers-1.0.2.dist-info/LICENSE
remove_outliers-1.0.2.dist-info/METADATA
remove_outliers-1.0.2.dist-info/WHEEL
remove_outliers-1.0.2.dist-info/entry_points.txt
remove_outliers-1.0.2.dist-info/top_level.txt
remove_outliers-1.0.2.dist-info/RECORD
